ws_bom_robot_app/__init__.py
ws_bom_robot_app/auth.py
ws_bom_robot_app/config.py
ws_bom_robot_app/cron_manager.py
ws_bom_robot_app/main.py
ws_bom_robot_app/subprocess_runner.py
ws_bom_robot_app/task_manager.py
ws_bom_robot_app/util.py
ws_bom_robot_app/llm/__init__.py
ws_bom_robot_app/llm/agent_context.py
ws_bom_robot_app/llm/agent_description.py
ws_bom_robot_app/llm/agent_handler.py
ws_bom_robot_app/llm/agent_lcel.py
ws_bom_robot_app/llm/api.py
ws_bom_robot_app/llm/defaut_prompt.py
ws_bom_robot_app/llm/evaluator.py
ws_bom_robot_app/llm/main.py
ws_bom_robot_app/llm/nebuly_handler.py
ws_bom_robot_app/llm/feedbacks/__init__.py
ws_bom_robot_app/llm/feedbacks/feedback_manager.py
ws_bom_robot_app/llm/models/__init__.py
ws_bom_robot_app/llm/models/api.py
ws_bom_robot_app/llm/models/base.py
ws_bom_robot_app/llm/models/feedback.py
ws_bom_robot_app/llm/models/kb.py
ws_bom_robot_app/llm/providers/__init__.py
ws_bom_robot_app/llm/providers/llm_manager.py
ws_bom_robot_app/llm/tools/__init__.py
ws_bom_robot_app/llm/tools/tool_builder.py
ws_bom_robot_app/llm/tools/tool_manager.py
ws_bom_robot_app/llm/tools/utils.py
ws_bom_robot_app/llm/tools/models/__init__.py
ws_bom_robot_app/llm/tools/models/main.py
ws_bom_robot_app/llm/utils/__init__.py
ws_bom_robot_app/llm/utils/agent.py
ws_bom_robot_app/llm/utils/chunker.py
ws_bom_robot_app/llm/utils/cleanup.py
ws_bom_robot_app/llm/utils/cms.py
ws_bom_robot_app/llm/utils/download.py
ws_bom_robot_app/llm/utils/print.py
ws_bom_robot_app/llm/utils/secrets.py
ws_bom_robot_app/llm/utils/webhooks.py
ws_bom_robot_app/llm/vector_store/__init__.py
ws_bom_robot_app/llm/vector_store/generator.py
ws_bom_robot_app/llm/vector_store/db/__init__.py
ws_bom_robot_app/llm/vector_store/db/base.py
ws_bom_robot_app/llm/vector_store/db/chroma.py
ws_bom_robot_app/llm/vector_store/db/faiss.py
ws_bom_robot_app/llm/vector_store/db/manager.py
ws_bom_robot_app/llm/vector_store/db/qdrant.py
ws_bom_robot_app/llm/vector_store/integration/__init__.py
ws_bom_robot_app-0.0.108.dist-info/METADATA
ws_bom_robot_app-0.0.108.dist-info/WHEEL
ws_bom_robot_app-0.0.108.dist-info/top_level.txt
ws_bom_robot_app-0.0.108.dist-info/RECORD
