Metadata-Version: 2.4
Name: ws_bom_robot_app
Version: 0.0.108
Summary: A FastAPI application serving ws bom/robot/llm platform ai.
Home-page: https://github.com/websolutespa/bom
Author: Websolute Spa
Author-email: dev@websolute.it
License: MIT
Classifier: Programming Language :: Python :: 3
Classifier: Operating System :: OS Independent
Requires-Python: >=3.12
Requires-Dist: standardwebhooks==1.0.0
Requires-Dist: apscheduler==3.11.1
Requires-Dist: aiofiles==25.1.0
Requires-Dist: pydantic==2.12.4
Requires-Dist: pydantic-settings==2.12.0
Requires-Dist: fastapi[standard]==0.121.1
Requires-Dist: chevron==0.14.0
Requires-Dist: msoffcrypto-tool==5.4.2
Requires-Dist: langchain==0.3.27
Requires-Dist: langchain-community==0.3.30
Requires-Dist: langchain-core==0.3.76
Requires-Dist: langchain-openai==0.3.33
Requires-Dist: langchain-anthropic==0.3.21
Requires-Dist: langchain-ibm==0.3.18
Requires-Dist: langchain-google-genai==2.1.12
Requires-Dist: langchain-google-vertexai==2.1.2
Requires-Dist: langchain-groq==0.3.8
Requires-Dist: langchain-ollama==0.3.8
Requires-Dist: openevals==0.1.2
Requires-Dist: faiss-cpu==1.12.0
Requires-Dist: chromadb==1.3.4
Requires-Dist: langchain-chroma==0.2.6
Requires-Dist: langchain-qdrant==0.2.1
Requires-Dist: qdrant-client[fastembed]==1.15.1
Requires-Dist: lark==1.3.1
Requires-Dist: chardet==5.2.0
Requires-Dist: unstructured==0.18.18
Requires-Dist: unstructured[image]
Requires-Dist: unstructured-ingest==1.2.21
Requires-Dist: unstructured-ingest[azure]
Requires-Dist: unstructured-ingest[confluence]
Requires-Dist: unstructured-ingest[dropbox]
Requires-Dist: unstructured-ingest[gcs]
Requires-Dist: unstructured-ingest[github]
Requires-Dist: unstructured-ingest[google_drive]
Requires-Dist: unstructured-ingest[jira]
Requires-Dist: unstructured-ingest[s3]
Requires-Dist: unstructured-ingest[sftp]
Requires-Dist: unstructured-ingest[sharepoint]
Requires-Dist: unstructured-ingest[slack]
Requires-Dist: html5lib==1.1
Requires-Dist: markdownify==1.2.0
Requires-Dist: duckduckgo-search==8.1.1
Requires-Dist: langchain-google-community==2.0.10
Requires-Dist: trafilatura==2.0.0
Dynamic: author
Dynamic: author-email
Dynamic: classifier
Dynamic: description
Dynamic: description-content-type
Dynamic: home-page
Dynamic: license
Dynamic: requires-dist
Dynamic: requires-python
Dynamic: summary
